setup.py
src/cube2crypto/__init__.py
src/cube2crypto/bit_test.py
src/cube2crypto/ecc_params.py
src/cube2crypto/extended_euclidean_gcd.py
src/cube2crypto/get_random_number.py
src/cube2crypto/gfield.py
src/cube2crypto/jacobian.py
src/cube2crypto/modular_inverse.py
src/cube2crypto/num_bits.py
src/cube2crypto/sboxes.py
src/cube2crypto/tiger.py
src/pycube2crypto.egg-info/PKG-INFO
src/pycube2crypto.egg-info/SOURCES.txt
src/pycube2crypto.egg-info/dependency_links.txt
src/pycube2crypto.egg-info/requires.txt
src/pycube2crypto.egg-info/top_level.txt