Metadata-Version: 1.1
Name: pycube2crypto
Version: 0.1
Summary: An implementation of the cube2 cryptography functions in pure python.
Home-page: https://github.com/fdChasm/pycube2crypto
Author: Chasm
Author-email: fd.chasm@gmail.com
License: MIT
Platform: UNKNOWN
Classifier: Development Status :: 3 - Alpha
Classifier: Topic :: Software Development :: Libraries :: Python Modules
Classifier: License :: OSI Approved :: MIT License
Classifier: Natural Language :: English
